plone.session-4.0.6-py3.13-nspkg.pth
plone/session/__init__.py
plone/session/configure.zcml
plone/session/hiddenprofiles.py
plone/session/interfaces.py
plone/session/meta.zcml
plone/session/profiles.zcml
plone/session/resources.zcml
plone/session/testing.py
plone/session/tktauth.py
plone/session/plugins/__init__.py
plone/session/plugins/secret.pt
plone/session/plugins/session.py
plone/session/plugins/session.zpt
plone/session/profiles/default/metadata.xml
plone/session/profiles/default/registry.xml
plone/session/profiles/uninstall/registry.xml
plone/session/resources/refreshsupport.js
plone/session/tests/__init__.py
plone/session/tests/configure.zcml
plone/session/tests/testDocTests.py
plone/session/tests/testPAS.py
plone_session-4.0.6.dist-info/METADATA
plone_session-4.0.6.dist-info/WHEEL
plone_session-4.0.6.dist-info/namespace_packages.txt
plone_session-4.0.6.dist-info/top_level.txt
plone_session-4.0.6.dist-info/RECORD
