Metadata-Version: 2.4
Name: plone.session
Version: 4.0.6
Summary: Session based auth tkt authentication for Zope
Home-page: https://github.com/plone/plone.session/
Author: Plone Foundation
Author-email: plone-developers@lists.sourceforge.net
License: BSD
Keywords: PAS session authentication Zope auth_tkt
Classifier: Development Status :: 5 - Production/Stable
Classifier: Environment :: Web Environment
Classifier: Framework :: Plone :: 6.0
Classifier: Framework :: Plone :: Core
Classifier: Framework :: Plone
Classifier: Framework :: Zope :: 5
Classifier: License :: OSI Approved :: BSD License
Classifier: Operating System :: OS Independent
Classifier: Programming Language :: Python :: 3.8
Classifier: Programming Language :: Python :: 3.9
Classifier: Programming Language :: Python :: 3.10
Classifier: Programming Language :: Python :: 3.11
Classifier: Programming Language :: Python
Classifier: Topic :: System :: Systems Administration :: Authentication/Directory
Requires-Python: >=3.8
Requires-Dist: plone.keyring
Requires-Dist: plone.protect
Requires-Dist: Products.GenericSetup
Requires-Dist: Products.PluggableAuthService
Requires-Dist: setuptools
Requires-Dist: Zope
Provides-Extra: test
Requires-Dist: plone.app.testing; extra == "test"
Requires-Dist: zope.publisher; extra == "test"
Dynamic: author
Dynamic: author-email
Dynamic: classifier
Dynamic: description
Dynamic: home-page
Dynamic: keywords
Dynamic: license
Dynamic: provides-extra
Dynamic: requires-dist
Dynamic: requires-python
Dynamic: summary
